{
  "count": 6,
  "results": [
    {
      "name": "arthur-morgan02",
      "workloads_access": "read_only",
      "last_editor": "string",
      "last_modified": "2019-08-24T14:15:22Z",
      "product_version": "1.0"
    },
    {
      "name": "arthur-morgan03",
      "workloads_access": "read_only",
      "last_editor": "string",
      "last_modified": "2019-08-24T14:15:22Z",
      "product_version": "1.0"
    },
    {
      "name": "arthur-morgan05",
      "workloads_access": "read_only",
      "last_editor": "string",
      "last_modified": "2019-08-24T14:15:22Z",
      "product_version": "1.0"
    },
    {
      "name": "arthur-morgan06",
      "workloads_access": "read_only",
      "last_editor": "string",
      "last_modified": "2019-08-24T14:15:22Z",
      "product_version": "1.0"
    },
    {
      "name": "blue-bilbo",
      "workloads_access": "read_write",
      "last_editor": "string",
      "last_modified": "2019-08-24T14:15:22Z",
      "product_version": "1.0"
    },
    {
      "name": "courageous-thunder",
      "workloads_access": "read_write",
      "last_editor": "string",
      "last_modified": "2019-08-24T14:15:22Z",
      "product_version": "1.0"
    }
  ]
}
